tcgplayer_client/__init__.py
tcgplayer_client/auth.py
tcgplayer_client/cache.py
tcgplayer_client/client.py
tcgplayer_client/config.py
tcgplayer_client/exceptions.py
tcgplayer_client/logging_config.py
tcgplayer_client/rate_limiter.py
tcgplayer_client/session_manager.py
tcgplayer_client/validation.py
tcgplayer_client/endpoints/__init__.py
tcgplayer_client/endpoints/catalog.py
tcgplayer_client/endpoints/inventory.py
tcgplayer_client/endpoints/orders.py
tcgplayer_client/endpoints/pricing.py
tcgplayer_client/endpoints/stores.py
tcgplayer_client-2.0.3.dist-info/licenses/LICENSE
tcgplayer_client-2.0.3.dist-info/METADATA
tcgplayer_client-2.0.3.dist-info/WHEEL
tcgplayer_client-2.0.3.dist-info/top_level.txt
tcgplayer_client-2.0.3.dist-info/RECORD
