Metadata-Version: 2.4
Name: tcgplayer_client
Version: 2.0.3
Summary: Python client library for TCGplayer API with async support, rate limiting, and comprehensive endpoint coverage
Author-email: Josh Wilhelmi <josh@gobby.ai>
Maintainer-email: Josh Wilhelmi <josh@gobby.ai>
License: MIT
Project-URL: Homepage, https://github.com/joshwilhelmi/tcgplayer-python
Project-URL: Documentation, https://github.com/joshwilhelmi/tcgplayer-python#readme
Project-URL: Repository, https://github.com/joshwilhelmi/tcgplayer-python
Project-URL: Issues, https://github.com/joshwilhelmi/tcgplayer-python/issues
Project-URL: Changelog, https://github.com/joshwilhelmi/tcgplayer-python/blob/main/CHANGELOG.md
Keywords: tcgplayer,api,trading-cards,async,mtg,pokemon,yugioh
Classifier: Development Status :: 5 - Production/Stable
Classifier: Intended Audience :: Developers
Classifier: Operating System :: OS Independent
Classifier: Programming Language :: Python :: 3
Classifier: Programming Language :: Python :: 3.8
Classifier: Programming Language :: Python :: 3.9
Classifier: Programming Language :: Python :: 3.10
Classifier: Programming Language :: Python :: 3.11
Classifier: Programming Language :: Python :: 3.12
Classifier: Topic :: Software Development :: Libraries :: Python Modules
Classifier: Topic :: Internet :: WWW/HTTP :: Dynamic Content
Classifier: Topic :: Games/Entertainment :: Board Games
Requires-Python: >=3.8
License-File: LICENSE
Requires-Dist: aiohttp>=3.8.0
Provides-Extra: dev
Requires-Dist: pytest>=7.0.0; extra == "dev"
Requires-Dist: pytest-asyncio>=0.21.0; extra == "dev"
Requires-Dist: pytest-cov>=4.0.0; extra == "dev"
Requires-Dist: black>=23.0.0; extra == "dev"
Requires-Dist: isort>=5.12.0; extra == "dev"
Requires-Dist: flake8>=6.0.0; extra == "dev"
Requires-Dist: mypy>=1.0.0; extra == "dev"
Provides-Extra: test
Requires-Dist: pytest>=7.0.0; extra == "test"
Requires-Dist: pytest-asyncio>=0.21.0; extra == "test"
Requires-Dist: pytest-cov>=4.0.0; extra == "test"
Dynamic: license-file
